README.txt
setup.cfg
setup.py
docs/HISTORY.txt
docs/LICENSE.GPL
docs/LICENSE.txt
docs/MANUAL.txt
raptus/__init__.py
raptus.article.discussion.egg-info/PKG-INFO
raptus.article.discussion.egg-info/SOURCES.txt
raptus.article.discussion.egg-info/dependency_links.txt
raptus.article.discussion.egg-info/entry_points.txt
raptus.article.discussion.egg-info/namespace_packages.txt
raptus.article.discussion.egg-info/not-zip-safe
raptus.article.discussion.egg-info/requires.txt
raptus.article.discussion.egg-info/top_level.txt
raptus/article/__init__.py
raptus/article/discussion/__init__.py
raptus/article/discussion/configure.zcml
raptus/article/discussion/conversation.py
raptus/article/discussion/profiles/default/metadata.xml