Metadata-Version: 1.0
Name: raptus.article.discussion
Version: 1.0b1
Summary: raptus.article.discussion include plone.app.discussion in the raptus.article
Home-page: http://raptus.com
Author: Raptus Ag
Author-email: dev@raptus.com
License: GPL
Platform: UNKNOWN
Classifier: Programming Language :: Python
